neph/__init__.py
neph/aws/__init__.py
neph/aws/edges/__init__.py
neph/aws/edges/core.py
neph/aws/edges/ec2.py
neph/aws/edges/iam.py
neph/aws/edges/iic.py
neph/aws/edges/lambdaf.py
neph/aws/edges/org.py
neph/aws/edges/rds.py
neph/aws/edges/ssm.py
neph/aws/equivalence.py
neph/aws/nodes/__init__.py
neph/aws/nodes/core.py
neph/aws/nodes/ec2.py
neph/aws/nodes/iam.py
neph/aws/nodes/iic.py
neph/aws/nodes/lambdaf.py
neph/aws/nodes/org.py
neph/aws/nodes/rds.py
neph/aws/nodes/s3.py
neph/aws/nodes/secretsmanager.py
neph/aws/nodes/ssm.py
neph/aws/other/__init__.py
neph/aws/other/fanouts.py
neph/aws/policies.py
neph/aws/principals.py
neph/aws/resources.py
neph/cdc.py
neph/cli.py
neph/collect.py
neph/data/columns.txt
neph/data/policies.zip
neph/db.py
neph/edges.py
neph/enrich.py
neph/exceptions.py
neph/fanout.py
neph/jsonl.py
neph/leads.py
neph/log.py
neph/nodes.py
neph/path.py
neph/plugins.py
neph/reporting.py
neph/settings.py
neph/sim.py
neph/utils.py
neph/workflow.py
neph-1.0.1.dist-info/LICENSE-3P.txt
neph-1.0.1.dist-info/LICENSE.txt
neph-1.0.1.dist-info/METADATA
neph-1.0.1.dist-info/WHEEL
neph-1.0.1.dist-info/entry_points.txt
neph-1.0.1.dist-info/RECORD
