Metadata-Version: 2.1
Name: neph
Version: 1.0.1
Summary: AWS attack path graphing tool
License: AGPL-3.0-only
Author: Evan Perotti
Author-email: evan.perotti@sra.io
Requires-Python: >=3.12,<4.0
Classifier: License :: OSI Approved :: GNU Affero General Public License v3
Classifier: Programming Language :: Python :: 3
Classifier: Programming Language :: Python :: 3.12
Classifier: Programming Language :: Python :: 3.13
Requires-Dist: fastapi[standard] (>=0.115.11,<0.116.0)
Requires-Dist: iamdata (>=0.1.202502201,<0.2.0)
Requires-Dist: neo4j (>=5.28.1,<6.0.0)
Requires-Dist: pydantic-settings (>=2.8.0,<3.0.0)
Requires-Dist: pyyaml (>=6.0.2,<7.0.0)
Requires-Dist: requests (>=2.32.3,<3.0.0)
